polundra/__init__.py
polundra/__main__.py
polundra/audio/__init__.py
polundra/audio/pulse.py
polundra/audio/utils.py
polundra/dispatcher.py
polundra/utils.py
polundra/visual/__init__.py
polundra/visual/dbus.py
polundra/visual/functions.py
polundra/visual/screen.py
polundra-0.1.7.dist-info/entry_points.txt
polundra-0.1.7.dist-info/LICENSE
polundra-0.1.7.dist-info/WHEEL
polundra-0.1.7.dist-info/METADATA
polundra-0.1.7.dist-info/RECORD
